odrpack/__init__.py
odrpack/odr_scipy.py
odrpack/exceptions.py
odrpack/__odrpack.cpython-313-x86_64-linux-musl.so
odrpack/result.py
odrpack/py.typed
odrpack/__odrpack.pyi
odrpack/odr_fortran.py
odrpack-0.3.5.dist-info/METADATA
odrpack-0.3.5.dist-info/LICENSE
odrpack-0.3.5.dist-info/WHEEL
odrpack-0.3.5.dist-info/RECORD
odrpack.libs/libopenblasp-r0-79c4374e.3.28.so
odrpack.libs/libgfortran-a63d0bbe.so.5.0.0
odrpack.libs/libquadmath-2ce5a29f.so.0.0.0
odrpack.libs/libstdc++-0d31ccbe.so.6.0.32
odrpack.libs/libgcc_s-a0b57c20.so.1
