Metadata-Version: 2.1
Name: odrpack
Version: 0.3.5
Summary: Package for weighted orthogonal distance regression (ODR).
Keywords: regression,statistics,mathematics
Author-Email: Hugo Vale <57530119+HugoMVale@users.noreply.github.com>
License: MIT License
Classifier: Development Status :: 1 - Planning
Classifier: Intended Audience :: Science/Research
Classifier: Operating System :: Microsoft :: Windows
Classifier: Operating System :: POSIX :: Linux
Classifier: Operating System :: MacOS
Classifier: License :: OSI Approved :: MIT License
Classifier: Programming Language :: Python
Classifier: Programming Language :: Python :: 3
Classifier: Programming Language :: Python :: 3.10
Classifier: Programming Language :: Python :: 3.11
Classifier: Programming Language :: Python :: 3.12
Classifier: Programming Language :: Python :: 3.13
Classifier: Topic :: Scientific/Engineering
Project-URL: Repository, https://github.com/HugoMVale/odrpack-python
Project-URL: Documentation, https://hugomvale.github.io/odrpack-python/
Requires-Python: >=3.10
Requires-Dist: numpy>=1.24
